kymodule/__init__.py
kymodule/example.py
kymodule/exceptions.py
kymodule-0.0.1.dist-info/LICENSE
kymodule-0.0.1.dist-info/METADATA
kymodule-0.0.1.dist-info/WHEEL
kymodule-0.0.1.dist-info/top_level.txt
kymodule-0.0.1.dist-info/RECORD
