Metadata-Version: 2.1
Name: kymodule
Version: 0.0.1
Summary: Demo project
Home-page: https://github.com/CHRISTMardochee/django-module
Author: MothinelKG
Author-email: kgmardochee@gmail.com
License: MIT
Keywords: core package
Platform: UNKNOWN
Classifier: Development Status :: 5 - Production/Stable
Classifier: License :: OSI Approved :: MIT License
Classifier: Programming Language :: Python :: 3
Classifier: Operating System :: OS Independent
Classifier: Intended Audience :: Developers
Requires-Dist: PyYAML
